<?xml version="1.0" encoding="utf-8" standalone="no"?>
<billStatus>
  <version>3.0.0</version>
  <bill>
    <number>104</number>
    <updateDate>2022-11-01T15:32:54Z</updateDate>
    <updateDateIncludingText>2022-11-01T15:32:54Z</updateDateIncludingText>
    <originChamber>House</originChamber>
    <type>HRES</type>
    <introducedDate>2019-02-06</introducedDate>
    <congress>116</congress>
    <cdata/>
    <committees>
      <item>
        <systemCode>hsgo00</systemCode>
        <name>Oversight and Accountability Committee</name>
        <chamber>House</chamber>
        <type>Standing</type>
        <activities>
          <item>
            <name>Referred to</name>
            <date>2019-02-06T15:01:25Z</date>
          </item>
        </activities>
      </item>
    </committees>
    <relatedBills>
      <item>
        <title>Expressing support for designation of the week beginning February 2, 2020, as "National Tribal Colleges and Universities Week".</title>
        <congress>116</congress>
        <number>824</number>
        <type>HRES</type>
        <latestAction>
          <actionDate>2020-01-30</actionDate>
          <text>Referred to the House Committee on Oversight and Reform.</text>
        </latestAction>
        <relationshipDetails>
          <item>
            <type>Related bill</type>
            <identifiedBy>CRS</identifiedBy>
          </item>
        </relationshipDetails>
      </item>
      <item>
        <title>A resolution designating the week beginning February 3, 2019, as "National Tribal Colleges and Universities Week".</title>
        <congress>116</congress>
        <number>37</number>
        <type>SRES</type>
        <latestAction>
          <actionDate>2019-01-31</actionDate>
          <text>Submitted in the Senate, considered, and agreed to without amendment and with a preamble by Voice Vote. (consideration: CR S815; text: CR S811)</text>
        </latestAction>
        <relationshipDetails>
          <item>
            <type>Related bill</type>
            <identifiedBy>CRS</identifiedBy>
          </item>
        </relationshipDetails>
      </item>
      <item>
        <title>A resolution designating the week beginning February 2, 2020, as "National Tribal Colleges and University Week".</title>
        <congress>116</congress>
        <number>491</number>
        <type>SRES</type>
        <latestAction>
          <actionDate>2020-02-11</actionDate>
          <text>Resolution agreed to in Senate without amendment and with a preamble by Voice Vote. (text: 02/05/2020 CR S943-944)</text>
        </latestAction>
        <relationshipDetails>
          <item>
            <type>Related bill</type>
            <identifiedBy>CRS</identifiedBy>
          </item>
        </relationshipDetails>
      </item>
    </relatedBills>
    <actions>
      <item>
        <actionDate>2019-02-06</actionDate>
        <text>Referred to the House Committee on Oversight and Reform.</text>
        <type>IntroReferral</type>
        <actionCode>H11100</actionCode>
        <sourceSystem>
          <code>2</code>
          <name>House floor actions</name>
        </sourceSystem>
        <committees>
          <item>
            <systemCode>hsgo00</systemCode>
            <name>Oversight and Accountability Committee</name>
          </item>
        </committees>
      </item>
      <item>
        <actionDate>2019-02-06</actionDate>
        <text>Introduced in House</text>
        <type>IntroReferral</type>
        <actionCode>Intro-H</actionCode>
        <sourceSystem>
          <code>9</code>
          <name>Library of Congress</name>
        </sourceSystem>
      </item>
      <item>
        <actionDate>2019-02-06</actionDate>
        <text>Introduced in House</text>
        <type>IntroReferral</type>
        <actionCode>1000</actionCode>
        <sourceSystem>
          <code>9</code>
          <name>Library of Congress</name>
        </sourceSystem>
      </item>
    </actions>
    <sponsors>
      <item>
        <bioguideId>O000171</bioguideId>
        <fullName>Rep. O'Halleran, Tom [D-AZ-1]</fullName>
        <firstName>Tom</firstName>
        <lastName>O'Halleran</lastName>
        <party>D</party>
        <state>AZ</state>
        <district>1</district>
        <isByRequest>N</isByRequest>
      </item>
    </sponsors>
    <cosponsors>
      <item>
        <bioguideId>C001053</bioguideId>
        <fullName>Rep. Cole, Tom [R-OK-4]</fullName>
        <firstName>Tom</firstName>
        <lastName>Cole</lastName>
        <party>R</party>
        <state>OK</state>
        <district>4</district>
        <sponsorshipDate>2019-02-06</sponsorshipDate>
        <isOriginalCosponsor>True</isOriginalCosponsor>
      </item>
      <item>
        <bioguideId>Y000033</bioguideId>
        <fullName>Rep. Young, Don [R-AK-At Large]</fullName>
        <firstName>DON</firstName>
        <lastName>YOUNG</lastName>
        <party>R</party>
        <state>AK</state>
        <middleName>E.</middleName>
        <district>0</district>
        <sponsorshipDate>2019-02-06</sponsorshipDate>
        <isOriginalCosponsor>True</isOriginalCosponsor>
      </item>
      <item>
        <bioguideId>T000484</bioguideId>
        <fullName>Rep. Torres Small, Xochitl [D-NM-2]</fullName>
        <firstName>Xochitl</firstName>
        <lastName>Torres Small</lastName>
        <party>D</party>
        <state>NM</state>
        <district>2</district>
        <sponsorshipDate>2019-02-06</sponsorshipDate>
        <isOriginalCosponsor>True</isOriginalCosponsor>
      </item>
      <item>
        <bioguideId>G000574</bioguideId>
        <fullName>Rep. Gallego, Ruben [D-AZ-7]</fullName>
        <firstName>Ruben</firstName>
        <lastName>Gallego</lastName>
        <party>D</party>
        <state>AZ</state>
        <district>7</district>
        <sponsorshipDate>2019-02-07</sponsorshipDate>
        <isOriginalCosponsor>False</isOriginalCosponsor>
      </item>
      <item>
        <bioguideId>M001160</bioguideId>
        <fullName>Rep. Moore, Gwen [D-WI-4]</fullName>
        <firstName>Gwen</firstName>
        <lastName>Moore</lastName>
        <party>D</party>
        <state>WI</state>
        <district>4</district>
        <sponsorshipDate>2019-02-07</sponsorshipDate>
        <isOriginalCosponsor>False</isOriginalCosponsor>
      </item>
      <item>
        <bioguideId>A000377</bioguideId>
        <fullName>Rep. Armstrong, Kelly [R-ND-At Large]</fullName>
        <firstName>Kelly</firstName>
        <lastName>Armstrong</lastName>
        <party>R</party>
        <state>ND</state>
        <district>0</district>
        <sponsorshipDate>2019-02-07</sponsorshipDate>
        <isOriginalCosponsor>False</isOriginalCosponsor>
      </item>
      <item>
        <bioguideId>B001301</bioguideId>
        <fullName>Rep. Bergman, Jack [R-MI-1]</fullName>
        <firstName>Jack</firstName>
        <lastName>Bergman</lastName>
        <party>R</party>
        <state>MI</state>
        <district>1</district>
        <sponsorshipDate>2019-02-07</sponsorshipDate>
        <isOriginalCosponsor>False</isOriginalCosponsor>
      </item>
      <item>
        <bioguideId>J000301</bioguideId>
        <fullName>Rep. Johnson, Dusty [R-SD-At Large]</fullName>
        <firstName>Dusty</firstName>
        <lastName>Johnson</lastName>
        <party>R</party>
        <state>SD</state>
        <district>0</district>
        <sponsorshipDate>2019-02-08</sponsorshipDate>
        <isOriginalCosponsor>False</isOriginalCosponsor>
      </item>
      <item>
        <bioguideId>P000258</bioguideId>
        <fullName>Rep. Peterson, Collin C. [D-MN-7]</fullName>
        <firstName>COLLIN</firstName>
        <lastName>PETERSON</lastName>
        <party>D</party>
        <state>MN</state>
        <middleName>C.</middleName>
        <district>7</district>
        <sponsorshipDate>2019-02-08</sponsorshipDate>
        <isOriginalCosponsor>False</isOriginalCosponsor>
      </item>
      <item>
        <bioguideId>K000381</bioguideId>
        <fullName>Rep. Kilmer, Derek [D-WA-6]</fullName>
        <firstName>Derek</firstName>
        <lastName>Kilmer</lastName>
        <party>D</party>
        <state>WA</state>
        <district>6</district>
        <sponsorshipDate>2019-02-13</sponsorshipDate>
        <isOriginalCosponsor>False</isOriginalCosponsor>
      </item>
      <item>
        <bioguideId>L000570</bioguideId>
        <fullName>Rep. Lujan, Ben Ray [D-NM-3]</fullName>
        <firstName>Ben</firstName>
        <lastName>Lujan</lastName>
        <party>D</party>
        <state>NM</state>
        <middleName>R.</middleName>
        <district>3</district>
        <sponsorshipDate>2019-02-13</sponsorshipDate>
        <isOriginalCosponsor>False</isOriginalCosponsor>
      </item>
      <item>
        <bioguideId>G000559</bioguideId>
        <fullName>Rep. Garamendi, John [D-CA-3]</fullName>
        <firstName>John</firstName>
        <lastName>Garamendi</lastName>
        <party>D</party>
        <state>CA</state>
        <district>3</district>
        <sponsorshipDate>2019-02-13</sponsorshipDate>
        <isOriginalCosponsor>False</isOriginalCosponsor>
      </item>
      <item>
        <bioguideId>H001080</bioguideId>
        <fullName>Rep. Haaland, Debra A. [D-NM-1]</fullName>
        <firstName>Debra</firstName>
        <lastName>Haaland</lastName>
        <party>D</party>
        <state>NM</state>
        <middleName>A.</middleName>
        <district>1</district>
        <sponsorshipDate>2019-02-13</sponsorshipDate>
        <isOriginalCosponsor>False</isOriginalCosponsor>
      </item>
      <item>
        <bioguideId>W000824</bioguideId>
        <fullName>Rep. Watkins, Steve [R-KS-2]</fullName>
        <firstName>Steve</firstName>
        <lastName>Watkins</lastName>
        <party>R</party>
        <state>KS</state>
        <district>2</district>
        <sponsorshipDate>2019-02-13</sponsorshipDate>
        <isOriginalCosponsor>False</isOriginalCosponsor>
      </item>
      <item>
        <bioguideId>G000579</bioguideId>
        <fullName>Rep. Gallagher, Mike [R-WI-8]</fullName>
        <firstName>Mike</firstName>
        <lastName>Gallagher</lastName>
        <party>R</party>
        <state>WI</state>
        <district>8</district>
        <sponsorshipDate>2019-03-05</sponsorshipDate>
        <isOriginalCosponsor>False</isOriginalCosponsor>
      </item>
    </cosponsors>
    <policyArea>
      <name>Native Americans</name>
    </policyArea>
    <subjects>
      <legislativeSubjects>
        <item>
          <name>Commemorative events and holidays</name>
        </item>
        <item>
          <name>Higher education</name>
        </item>
        <item>
          <name>Indian social and development programs</name>
        </item>
        <item>
          <name>Minority education</name>
        </item>
      </legislativeSubjects>
      <policyArea>
        <name>Native Americans</name>
      </policyArea>
    </subjects>
    <summaries>
      <summary>
        <versionCode>00</versionCode>
        <actionDate>2019-02-06</actionDate>
        <actionDesc>Introduced in House</actionDesc>
        <updateDate>2020-02-14T15:10:12Z</updateDate>
        <text><![CDATA[ <p>This resolution supports the designation of National Tribal Colleges and Universities Week.</p>]]></text>
      </summary>
    </summaries>
    <title>Expressing support for designation of the week beginning February 3, 2019, as "National Tribal Colleges and Universities Week".</title>
    <titles>
      <item>
        <titleType>Display Title</titleType>
        <title>Expressing support for designation of the week beginning February 3, 2019, as "National Tribal Colleges and Universities Week".</title>
      </item>
      <item>
        <titleType>Official Title as Introduced</titleType>
        <title>Expressing support for designation of the week beginning February 3, 2019, as "National Tribal Colleges and Universities Week".</title>
        <billTextVersionName>Introduced in House</billTextVersionName>
        <billTextVersionCode>IH</billTextVersionCode>
      </item>
    </titles>
    <textVersions>
      <item>
        <type>Introduced in House</type>
        <date>2019-02-06T05:00:00Z</date>
        <formats>
          <item>
            <url>https://www.govinfo.gov/content/pkg/BILLS-116hres104ih/xml/BILLS-116hres104ih.xml</url>
          </item>
        </formats>
      </item>
    </textVersions>
    <latestAction>
      <actionDate>2019-02-06</actionDate>
      <text>Referred to the House Committee on Oversight and Reform.</text>
    </latestAction>
  </bill>
  <dublinCore xmlns:dc="http://purl.org/dc/elements/1.1/">
    <dc:format>text/xml</dc:format>
    <dc:language>EN</dc:language>
    <dc:rights>Pursuant to Title 17 Section 105 of the United States Code, this file is not subject to copyright protection and is in the public domain.</dc:rights>
    <dc:contributor>Congressional Research Service, Library of Congress</dc:contributor>
    <dc:description>This file contains bill summaries and statuses for federal legislation. A bill summary describes the most significant provisions of a piece of legislation and details the effects the legislative text may have on current law and federal programs. Bill summaries are authored by the Congressional Research Service (CRS) of the Library of Congress. As stated in Public Law 91-510 (2 USC 166 (d)(6)), one of the duties of CRS is "to prepare summaries and digests of bills and resolutions of a public general nature introduced in the Senate or House of Representatives". For more information, refer to the User Guide that accompanies this file.</dc:description>
  </dublinCore>
</billStatus>
