{
  "bill_id": "hr1096-103",
  "congress": 103,
  "type": "hr",
  "number": "1096",
  "version": "ih",
  "format": "html",
  "source_url": "https://www.govinfo.gov/content/pkg/BILLS-103hr1096ih/html/BILLS-103hr1096ih.htm",
  "short_title": null,
  "official_title": "To amend the Internal Revenue Code of 1986 to provide that distributions to involuntarily unemployed individuals from individual retirement accounts will not be subject to the additional tax on early distributions.",
  "status": "REFERRED",
  "bytes": 2668
}