{
  "bill_id": "hr1248-103",
  "congress": 103,
  "type": "hr",
  "number": "1248",
  "version": "ih",
  "format": "html",
  "source_url": "https://www.govinfo.gov/content/pkg/BILLS-103hr1248ih/html/BILLS-103hr1248ih.htm",
  "short_title": "Trade Agreements Compliance Act of 1993",
  "official_title": "To amend the Trade Act of 1974 to provide for the review of the extent to which foreign countries are in compliance with bilateral trade agreements with the United States.",
  "status": "REFERRED",
  "bytes": 7594
}