{
  "bill_id": "hr1396-103",
  "congress": 103,
  "type": "hr",
  "number": "1396",
  "version": "ih",
  "format": "html",
  "source_url": "https://www.govinfo.gov/content/pkg/BILLS-103hr1396ih/html/BILLS-103hr1396ih.htm",
  "short_title": "House of Representatives Election Campaign Reform Act of 1993",
  "official_title": "To amend the Federal Election Campaign Act of 1971 to provide for a voluntary system of spending limits and partial public financing for House of Representatives election campaigns, to prohibit contributions by multicandidate political committees, and for other purposes.",
  "status": "REFERRED",
  "bytes": 72183
}