{
  "bill_id": "hr1409-103",
  "congress": 103,
  "type": "hr",
  "number": "1409",
  "version": "ih",
  "format": "html",
  "source_url": "https://www.govinfo.gov/content/pkg/BILLS-103hr1409ih/html/BILLS-103hr1409ih.htm",
  "short_title": "Foreign Tax Simplification Act of 1993",
  "official_title": "To amend the Internal Revenue Code of 1986 to reduce compliance costs and administrative burdens in connection with foreign taxes, and for other purposes.",
  "status": "REFERRED",
  "bytes": 13579
}